clang_tool_chain/__init__.py
clang_tool_chain/__version__.py
clang_tool_chain/archive.py
clang_tool_chain/archive_cache.py
clang_tool_chain/checksums.py
clang_tool_chain/cli.py
clang_tool_chain/cli_args.py
clang_tool_chain/cli_parsers.py
clang_tool_chain/component_db.py
clang_tool_chain/downloader.py
clang_tool_chain/env_breadcrumbs.py
clang_tool_chain/env_utils.py
clang_tool_chain/fetch.py
clang_tool_chain/installer.py
clang_tool_chain/interrupt_utils.py
clang_tool_chain/llvm_versions.py
clang_tool_chain/logging_config.py
clang_tool_chain/manifest.py
clang_tool_chain/parallel_download.py
clang_tool_chain/path_utils.py
clang_tool_chain/paths.py
clang_tool_chain/permissions.py
clang_tool_chain/sccache_runner.py
clang_tool_chain/settings_warnings.py
clang_tool_chain/wrapper.py
clang_tool_chain/abi/__init__.py
clang_tool_chain/abi/windows_gnu.py
clang_tool_chain/abi/windows_msvc.py
clang_tool_chain/commands/__init__.py
clang_tool_chain/commands/entry_points.py
clang_tool_chain/deployment/__init__.py
clang_tool_chain/deployment/base_deployer.py
clang_tool_chain/deployment/dll_deployer.py
clang_tool_chain/deployment/dll_detector.py
clang_tool_chain/deployment/dylib_deployer.py
clang_tool_chain/deployment/factory.py
clang_tool_chain/deployment/libdeploy.py
clang_tool_chain/deployment/so_deployer.py
clang_tool_chain/directives/__init__.py
clang_tool_chain/directives/parser.py
clang_tool_chain/execution/__init__.py
clang_tool_chain/execution/arg_transformers.py
clang_tool_chain/execution/build.py
clang_tool_chain/execution/build_pipeline.py
clang_tool_chain/execution/core.py
clang_tool_chain/execution/cosmocc.py
clang_tool_chain/execution/emscripten.py
clang_tool_chain/execution/iwyu.py
clang_tool_chain/execution/lldb.py
clang_tool_chain/execution/nodejs_resolver.py
clang_tool_chain/execution/platform_executor.py
clang_tool_chain/execution/sanitizer_env.py
clang_tool_chain/installers/__init__.py
clang_tool_chain/installers/base.py
clang_tool_chain/installers/clang.py
clang_tool_chain-1.1.0.dist-info/METADATA
clang_tool_chain-1.1.0.dist-info/WHEEL
clang_tool_chain-1.1.0.dist-info/entry_points.txt
clang_tool_chain-1.1.0.dist-info/licenses/LICENSE
clang_tool_chain-1.1.0.dist-info/RECORD
