Metadata-Version: 2.4
Name: clang-tool-chain
Version: 1.1.0
Summary: Clang Tool Chain - C/C++ compilation toolchain utilities
Project-URL: Homepage, https://github.com/zackees/clang-tool-chain
Project-URL: Repository, https://github.com/zackees/clang-tool-chain
Project-URL: Issues, https://github.com/zackees/clang-tool-chain/issues
Author: Zachary Vorhies
Maintainer: Zachary Vorhies
License-Expression: Apache-2.0
License-File: LICENSE
Keywords: c,clang,compiler,cpp,toolchain
Classifier: Development Status :: 3 - Alpha
Classifier: Intended Audience :: Developers
Classifier: License :: OSI Approved :: Apache Software License
Classifier: Programming Language :: Python :: 3
Classifier: Programming Language :: Python :: 3.10
Classifier: Programming Language :: Python :: 3.11
Classifier: Programming Language :: Python :: 3.12
Classifier: Programming Language :: Python :: 3.13
Classifier: Topic :: Software Development :: Build Tools
Classifier: Topic :: Software Development :: Compilers
Requires-Python: >=3.10
Requires-Dist: fasteners>=0.19.0
Requires-Dist: httpx>=0.27.0
Requires-Dist: meson>=1.0.0
Requires-Dist: pyzstd>=0.16.0
Requires-Dist: setenvironment>=1.1.0
Requires-Dist: uv-iso-env>=1.0.0
Provides-Extra: dev
Requires-Dist: flake8>=7.0.0; extra == 'dev'
Requires-Dist: mypy>=1.8.0; extra == 'dev'
Requires-Dist: pyright>=1.1.350; extra == 'dev'
Requires-Dist: pytest-cov>=4.1.0; extra == 'dev'
Requires-Dist: pytest-timeout>=2.3.0; extra == 'dev'
Requires-Dist: pytest-xdist>=3.5.0; extra == 'dev'
Requires-Dist: pytest>=8.0.0; extra == 'dev'
Requires-Dist: ruff>=0.3.0; extra == 'dev'
Requires-Dist: sccache>=0.7.0; extra == 'dev'
Provides-Extra: sccache
Requires-Dist: sccache>=0.7.0; extra == 'sccache'
